blockeval/__init__.py
blockeval/analysis.py
blockeval/utils.py
blockeval-0.1.0.dist-info/LICENSE
blockeval-0.1.0.dist-info/METADATA
blockeval-0.1.0.dist-info/WHEEL
blockeval-0.1.0.dist-info/top_level.txt
blockeval-0.1.0.dist-info/RECORD
