Metadata-Version: 2.1
Name: blockeval
Version: 0.1.0
Summary: Analyze campaigns with segments derived from a predictive model, an uplift score, or any business rule.
Home-page: https://github.com/cvs-health/blockeval
Author: d'Acremont Mathieu, Audrey Lee
Author-email: dacremontm@aetna.com, leey@cvshealth.com
License: Apache 2.0
Requires-Python: >=3.7
License-File: LICENSE
Requires-Dist: numpy >=1.18.1
Requires-Dist: pandas >=1.0.1
Requires-Dist: scipy >=1.4.1
Requires-Dist: statsmodels >=0.11.1
